byted_overpass_webcast_storage_solution/__init__.py
byted_overpass_webcast_storage_solution-0.0.1.dist-info/METADATA
byted_overpass_webcast_storage_solution-0.0.1.dist-info/WHEEL
byted_overpass_webcast_storage_solution-0.0.1.dist-info/top_level.txt
byted_overpass_webcast_storage_solution-0.0.1.dist-info/RECORD
